seqiolib/__init__.py
seqiolib/encoder.py
seqiolib/seqiolib.py
seqiolib/sequence.py
seqiolib/sequence.py~44e6a16e35f68fdbf47cf51b43c55c2b185689d5
seqiolib/utils/__init__.py
seqiolib/utils/io.py
seqiolib/utils/utils.py
seqiolib-0.2.4.dist-info/AUTHORS.rst
seqiolib-0.2.4.dist-info/LICENSE
seqiolib-0.2.4.dist-info/METADATA
seqiolib-0.2.4.dist-info/WHEEL
seqiolib-0.2.4.dist-info/top_level.txt
seqiolib-0.2.4.dist-info/RECORD
