Metadata-Version: 2.1
Name: seqiolib
Version: 0.2.4
Summary: Library to read, write sequence, variants, regions to use them for training of machine learning algorithms.
Home-page: https://github.com/visze/seqiolib
Author: Max Schubach
Author-email: max.schubach@bih-charite.de
License: MIT license
Keywords: seqiolib
Platform: UNKNOWN
Classifier: Development Status :: 2 - Pre-Alpha
Classifier: Intended Audience :: Developers
Classifier: License :: OSI Approved :: MIT License
Classifier: Natural Language :: English
Classifier: Programming Language :: Python :: 3
Classifier: Programming Language :: Python :: 3.5
Classifier: Programming Language :: Python :: 3.6
Classifier: Programming Language :: Python :: 3.7
Requires-Python: >=3.5
License-File: LICENSE
License-File: AUTHORS.rst
Requires-Dist: pyfaidx
Requires-Dist: numpy
Requires-Dist: tensorflow
